{
    "metadata": {},
    "knowledge graph": {
        "entities": [],
        "relations": {
            "Solar energy": [
                {
                    "Relation": "is generated by",
                    "Object": "Photovoltaic cells",
                    "Description": "Photovoltaic cells convert sunlight into electricity, generating solar energy."
                },
                {
                    "Relation": "is captured by",
                    "Object": "Solar panels",
                    "Description": "Solar panels capture sunlight and convert it into usable energy, contributing to solar energy production."
                },
                {
                    "Relation": "is harnessed by",
                    "Object": "Solar power plants",
                    "Description": "Solar power plants utilize solar energy to generate electricity on a large scale."
                },
                {
                    "Relation": "is the source of",
                    "Object": "Solar radiation",
                    "Description": "Solar radiation is the primary source of solar energy, providing the energy needed for various solar technologies."
                }
            ]
        }
    }
}