{
    "metadata": {},
    "knowledge graph": {
        "entity": "Niamey",
        "relations": [
            {
                "Relation": "show",
                "Subject": "Niamey",
                "Object": "variability",
                "Description": "Niamey and Zinder, located at \nlower latitudes, show less variability across \nthe year, hence making them excellent \nlocations for harnessing solar energy."
            },
            {
                "Relation": "make",
                "Subject": "analysis",
                "Object": "\n",
                "Description": "A financial analysis has been made \nas part of the pre-feasibility study of a \n20 MW grid-connected solar PV system \nnear Niamey under negotiation at pres\u0002ent."
            },
            {
                "Relation": "use",
                "Subject": "\n",
                "Object": "solar",
                "Description": "Many \nin Niamey are already using solar to cope \nwith rolling blackouts."
            }
        ]
    }
}